{"id":"0d2bd106-f214-4b6d-9c20-40252a32eb17","question":{"id":"0d2bd106-f214-4b6d-9c20-40252a32eb17","date":1446332400000,"segment":1,"question":"I am?","labelLeft":"anonymous","labelRight":"unique","labelTop":"electrified","labelBottom":"hibernated","priority":2},"size":0,"answers":[{"participant":"18612bfa-b70a-4c3c-ad2d-3d3438159464","question":"0d2bd106-f214-4b6d-9c20-40252a32eb17","x":0.47733333333333333,"y":-0.46236559139784944,"latitude":52.49091438191742,"longitude":13.37265175951355,"date":1446384553887,"mode":"Word","text":"Wifi","heartrate":147.78460703690203,"participant_":{"id":"18612bfa-b70a-4c3c-ad2d-3d3438159464","firstName":"Dimitri","lastName":"Nieuwenhuizen","gender":"male","notificationToken":null,"age":0,"hidden":false,"dailyHeartrates":null},"question_":null},{"participant":"3b684a5a-1141-4493-88be-fa346a91480c","question":"0d2bd106-f214-4b6d-9c20-40252a32eb17","x":-0.25333333333333335,"y":-0.47465437788018433,"latitude":52.5475555701733,"longitude":13.4015856535125,"date":1446395422787,"mode":"Sound","text":null,"heartrate":161.40444226077184,"participant_":{"id":"3b684a5a-1141-4493-88be-fa346a91480c","firstName":"Martin","lastName":"Walton","gender":"male","notificationToken":null,"age":0,"hidden":false,"dailyHeartrates":null},"question_":null},{"participant":"2dc087d7-bd87-4a10-b65a-06138436c538","question":"0d2bd106-f214-4b6d-9c20-40252a32eb17","x":0.37066666666666664,"y":0.2872503840245776,"latitude":52.49074211091508,"longitude":13.36953508315525,"date":1446384593904,"mode":"Sound","text":null,"heartrate":100.93639470472644,"participant_":{"id":"2dc087d7-bd87-4a10-b65a-06138436c538","firstName":"Marijke","lastName":"Cobbenhagen","gender":"female","notificationToken":null,"age":0,"hidden":false,"dailyHeartrates":null},"question_":null}],"xMean":0.19822222222222222,"yMean":-0.21658986175115205,"xDeviation":0.15577125925925928,"yDeviation":0.1904289985158128}