{"id":"4b314662-634b-40e4-b697-fcedf455bc7a","question":{"id":"4b314662-634b-40e4-b697-fcedf455bc7a","date":1446332400000,"segment":0,"question":"I feel?","labelLeft":"consolation","labelRight":"beauty","labelTop":"reality","labelBottom":"delusion","priority":1},"size":0,"answers":[{"participant":"18612bfa-b70a-4c3c-ad2d-3d3438159464","question":"4b314662-634b-40e4-b697-fcedf455bc7a","x":0.7546666666666667,"y":0.38863287250384027,"latitude":52.49252131982586,"longitude":13.35846221296579,"date":1446370109545,"mode":"Photo","text":null,"heartrate":159.26072839698963,"participant_":{"id":"18612bfa-b70a-4c3c-ad2d-3d3438159464","firstName":"Dimitri","lastName":"Nieuwenhuizen","gender":"male","notificationToken":null,"age":0,"hidden":false,"dailyHeartrates":null},"question_":null},{"participant":"2dc087d7-bd87-4a10-b65a-06138436c538","question":"4b314662-634b-40e4-b697-fcedf455bc7a","x":0.5466666666666666,"y":-0.47772657450076805,"latitude":52.49398480522618,"longitude":13.36130000422364,"date":1446367765699,"mode":"Photo","text":null,"heartrate":113.92339076443132,"participant_":{"id":"2dc087d7-bd87-4a10-b65a-06138436c538","firstName":"Marijke","lastName":"Cobbenhagen","gender":"female","notificationToken":null,"age":0,"hidden":false,"dailyHeartrates":null},"question_":null}],"xMean":0.6506666666666667,"yMean":-0.044546850998463894,"xDeviation":0.021632000000000016,"yDeviation":0.37528934570706535}