{"id":"7920dc09-7b6f-4f10-8374-519d2c66641b","question":{"id":"7920dc09-7b6f-4f10-8374-519d2c66641b","date":1447542000000,"segment":1,"question":"I am?","labelLeft":"anonymous","labelRight":"unique","labelTop":"electrified","labelBottom":"hibernated","priority":2},"size":0,"answers":[{"participant":"18612bfa-b70a-4c3c-ad2d-3d3438159464","question":"7920dc09-7b6f-4f10-8374-519d2c66641b","x":0.38666666666666666,"y":-0.029185867895545316,"latitude":52.38106341401647,"longitude":4.60393316279623,"date":1447591476097,"mode":"Sound","text":null,"heartrate":166.72584553325316,"participant_":{"id":"18612bfa-b70a-4c3c-ad2d-3d3438159464","firstName":"Dimitri","lastName":"Nieuwenhuizen","gender":"male","notificationToken":null,"age":0,"hidden":false,"dailyHeartrates":null},"question_":null},{"participant":"2dc087d7-bd87-4a10-b65a-06138436c538","question":"7920dc09-7b6f-4f10-8374-519d2c66641b","x":0.25866666666666666,"y":-0.29339477726574503,"latitude":52.37352046312255,"longitude":4.905798478346088,"date":1447592517615,"mode":"Word","text":"OK","heartrate":159.08182687574373,"participant_":{"id":"2dc087d7-bd87-4a10-b65a-06138436c538","firstName":"Marijke","lastName":"Cobbenhagen","gender":"female","notificationToken":null,"age":0,"hidden":false,"dailyHeartrates":null},"question_":null},{"participant":"063b6fe5-cdd1-42a8-b2b7-bc0dad72d832","question":"7920dc09-7b6f-4f10-8374-519d2c66641b","x":0.275,"y":-0.41810344827586204,"latitude":52.48000336736003,"longitude":13.44581070658729,"date":1447594105032,"mode":"Photo","text":null,"heartrate":97.17754454017916,"participant_":{"id":"063b6fe5-cdd1-42a8-b2b7-bc0dad72d832","firstName":"Antonia","lastName":"Barnett-McIntosh","gender":"female","notificationToken":null,"age":0,"hidden":false,"dailyHeartrates":null},"question_":null}],"xMean":0.30677777777777776,"yMean":-0.24689469781238413,"xDeviation":0.004853370370370369,"yDeviation":0.039435914124096694}